[{
    "text": "饮料",
    "children": [
        {
            "text": "哇哈哈矿泉水",
            "id": 1
        },
        {
            "text": "农夫山泉矿泉水",
            "id": 2
        },
        {
            "text": "康师傅冰红茶",
            "id": 3
        },
        {
            "text": "尖叫",
            "id": 4
        }
    ]
},{
    "text": "零食",
    "children": [
        {
            "text": "卫龙辣条",
            "id": 1
        },
        {
            "text": "乐事薯片",
            "id": 2
        },
        {
            "text": "方便面",
            "id": 3
        },
        {
            "text": "口香糖",
            "id": 4
        }
    ]
}]